LICENSE
MANIFEST.in
README.rst
changelog.rst
setup.py
docs/Makefile
docs/changelog.rst
docs/conf.py
docs/forkme.rst
docs/index.rst
docs/make.bat
lcppolicy_cracklib/__init__.py
lcppolicy_cracklib.egg-info/PKG-INFO
lcppolicy_cracklib.egg-info/SOURCES.txt
lcppolicy_cracklib.egg-info/dependency_links.txt
lcppolicy_cracklib.egg-info/requires.txt
lcppolicy_cracklib.egg-info/top_level.txt
tests/disable.py
tests/disable.pyc
tests/test_ppolicy.py
tests/__pycache__/test_ppolicy.cpython-27-PYTEST.pyc
tests/resources/cracklib_dict.hwm
tests/resources/cracklib_dict.pwd
tests/resources/cracklib_dict.pwi
tests/resources/false_dict.hwm
tests/resources/false_dict.pwd
tests/resources/false_dict.pwi