Metadata-Version: 1.1
Name: lcppolicy-cracklib
Version: 0.1.0
Summary: Cracklib password policy plugin for LdapCherry.
Home-page: https://github.com/kakwa/ldapcherry-ppolicy-cracklib
Author: Pierre-Francois Carpentier
Author-email: carpentier.pf@gmail.com
License: The MIT License (MIT)
